datacatalog/__init__.py
datacatalog/service_pb2.py
datacatalog/service_pb2_grpc.py
achan_test-0.0.1b8.dist-info/LICENSE
achan_test-0.0.1b8.dist-info/METADATA
achan_test-0.0.1b8.dist-info/NOTICE
achan_test-0.0.1b8.dist-info/WHEEL
achan_test-0.0.1b8.dist-info/top_level.txt
achan_test-0.0.1b8.dist-info/RECORD
